{
  "caption": "More ad spend does not fix a broken shop. It funds the leak faster.\n\nEvery dollar you add pushes more leads into the same slow follow-up. Double your budget and you roughly double the number of leads going cold before anyone calls them back.\n\nIndustry lead-response research shows only 17% of service businesses answer a new lead within an hour. Respond in under 5 minutes instead and you close at nearly double the rate.\n\nBefore you raise your ad budget, audit how fast your team actually responds. Fix the leak. Then scale.\n\nDM \"SCALE\" for that audit.\n\n#ServiceBusiness #LeadGeneration #SpeedToLead #HomeServices #BusinessGrowth",
  "format": "reel",
  "rationale": "Reels still carry the reach edge for cold audiences, and this stakes out a sharp, unclaimed brand POV (scaling ads before fixing follow-up burns money faster) that no past post has argued directly.",
  "category": "contrarian_pov",
  "experiment": null,
  "video": "published/2026-07-13/post1_reel/reel.mp4",
  "cover": "published/2026-07-13/post1_reel/cover.jpg",
  "story": "published/2026-07-13/post1_reel/story.jpg"
}